recite/__init__.py
recite/console.py
recite/main.py
recite/py.typed
recite/runner.py
recite/step.py
recite-0.2.2.dist-info/entry_points.txt
recite-0.2.2.dist-info/LICENSE
recite-0.2.2.dist-info/WHEEL
recite-0.2.2.dist-info/METADATA
recite-0.2.2.dist-info/RECORD
