Metadata-Version: 2.1
Name: recite
Version: 0.2.2
Summary: Publish your poetry-based projects, without missing important steps
Home-page: https://github.com/dobraczka/recite
License: MIT
Keywords: releasing,publishing,packaging
Author: Daniel Obraczka
Author-email: obraczka@informatik.uni-leipzig.de
Requires-Python: >=3.10,<4.0
Classifier: Development Status :: 4 - Beta
Classifier: License :: OSI Approved :: MIT License
Classifier: Programming Language :: Python
Classifier: Programming Language :: Python :: 3
Classifier: Programming Language :: Python :: 3.10
Classifier: Programming Language :: Python :: 3.11
Classifier: Programming Language :: Python :: 3 :: Only
Classifier: Programming Language :: Python :: 3.10
Classifier: Programming Language :: Python :: 3.8
Classifier: Programming Language :: Python :: 3.9
Provides-Extra: docs
Requires-Dist: gitpython (>=3.1.30,<4.0.0)
Requires-Dist: mkdocs (>=1.4.2,<2.0.0) ; extra == "docs"
Requires-Dist: mkdocs-material (>=9.0.9,<10.0.0) ; extra == "docs"
Requires-Dist: rich (>=13.1.0,<14.0.0)
Requires-Dist: toml (>=0.10.2,<0.11.0)
Requires-Dist: typer (>=0.7.0,<0.8.0)
Project-URL: Bug Tracker, https://github.com/dobraczka/recite/issues
Project-URL: Documentation, https://recite.readthedocs.io
Project-URL: Repository, https://github.com/dobraczka/recite
Project-URL: Source, https://github.com/dobraczka/recite
